cryptojwt/__init__.py
cryptojwt/exception.py
cryptojwt/jwt.py
cryptojwt/jwx.py
cryptojwt/key_bundle.py
cryptojwt/key_issuer.py
cryptojwt/key_jar.py
cryptojwt/simple_jwt.py
cryptojwt/utils.py
cryptojwt/jwe/__init__.py
cryptojwt/jwe/aes.py
cryptojwt/jwe/exception.py
cryptojwt/jwe/fernet.py
cryptojwt/jwe/jwe.py
cryptojwt/jwe/jwe_ec.py
cryptojwt/jwe/jwe_hmac.py
cryptojwt/jwe/jwe_rsa.py
cryptojwt/jwe/jwekey.py
cryptojwt/jwe/jwenc.py
cryptojwt/jwe/rsa.py
cryptojwt/jwe/utils.py
cryptojwt/jwk/__init__.py
cryptojwt/jwk/asym.py
cryptojwt/jwk/ec.py
cryptojwt/jwk/hmac.py
cryptojwt/jwk/jwk.py
cryptojwt/jwk/okp.py
cryptojwt/jwk/rsa.py
cryptojwt/jwk/utils.py
cryptojwt/jwk/wrap.py
cryptojwt/jwk/x509.py
cryptojwt/jws/__init__.py
cryptojwt/jws/dsa.py
cryptojwt/jws/eddsa.py
cryptojwt/jws/exception.py
cryptojwt/jws/hmac.py
cryptojwt/jws/jws.py
cryptojwt/jws/pss.py
cryptojwt/jws/rsa.py
cryptojwt/jws/utils.py
cryptojwt/serialize/__init__.py
cryptojwt/serialize/item.py
cryptojwt/tools/__init__.py
cryptojwt/tools/jwtpeek.py
cryptojwt/tools/keyconv.py
cryptojwt/tools/keygen.py
cryptojwt-1.10.0.dist-info/METADATA
cryptojwt-1.10.0.dist-info/WHEEL
cryptojwt-1.10.0.dist-info/entry_points.txt
cryptojwt-1.10.0.dist-info/licenses/LICENSE
cryptojwt-1.10.0.dist-info/RECORD
