Metadata-Version: 2.4
Name: cryptojwt
Version: 1.10.0
Summary: Python implementation of JWT, JWE, JWS and JWK
Author-email: Roland Hedberg <roland@catalogix.se>
License-Expression: Apache-2.0
License-File: LICENSE
Requires-Python: <4.0,>=3.9
Requires-Dist: cryptography>=3.4.6
Requires-Dist: requests>=2.25.1
